{"type": "FeatureCollection", "features": [{"type": "Feature", "properties": {"filename": "DJI_20250612095521_0040_D.JPG", "prediction": "99.63%", "classification": "THIS PICTURE HAS Oak Wilt", "latitude": 41.92701533333333, "longitude": -86.58233569444444}, "geometry": {"type": "Point", "coordinates": [-86.58233569444444, 41.92701533333333]}}, {"type": "Feature", "properties": {"filename": "DJI_20250612104705_0070_D.JPG", "prediction": "99.96%", "classification": "THIS PICTURE HAS Oak Wilt", "latitude": 41.91900094444444, "longitude": -86.58524719444443}, "geometry": {"type": "Point", "coordinates": [-86.58524719444443, 41.91900094444444]}}, {"type": "Feature", "properties": {"filename": "DJI_20250612104720_0080_D.JPG", "prediction": "89.59%", "classification": "POSSIBILITY OF Oak Wilt", "latitude": 41.91711380555555, "longitude": -86.58648408333333}, "geometry": {"type": "Point", "coordinates": [-86.58648408333333, 41.91711380555555]}}]}