{"type": "FeatureCollection", "features": [{"type": "Feature", "properties": {"filename": "DJI_20250612095521_0040_D.JPG", "prediction": "99.63%", "classification": "THIS PICTURE HAS Oak Wilt", "latitude": 41.92701533333333, "longitude": -86.58233569444444}, "geometry": {"type": "Point", "coordinates": [-86.58233569444444, 41.92701533333333]}}]}